itk/Configuration/IOMeshSTLConfig.py
itk/Configuration/IOMeshSTL_snake_case.py
itk/IOMeshSTLPython.py
itk/_IOMeshSTLPython.abi3.so
itk/itkSTLMeshIOPython.py
itk_iomeshstl-3.0.1.dist-info/METADATA
itk_iomeshstl-3.0.1.dist-info/WHEEL
itk_iomeshstl-3.0.1.dist-info/licenses/LICENSE
itk_iomeshstl-3.0.1.dist-info/RECORD
