Metadata-Version: 2.1
Name: itk-iomeshstl
Version: 3.0.1
Summary: MeshIO class to read and write ITK meshes into STL files.
Keywords: itk,InsightToolkit,STL,Mesh
Author-Email: =?utf-8?b?THVpcyBJYsOhw7Fleg==?= <community@itk.org>
License:                                  Apache License
Classifier: Development Status :: 4 - Beta
Classifier: Intended Audience :: Developers
Classifier: Intended Audience :: Education
Classifier: Intended Audience :: Healthcare Industry
Classifier: Intended Audience :: Science/Research
Classifier: License :: OSI Approved :: Apache Software License
Classifier: Operating System :: Android
Classifier: Operating System :: MacOS
Classifier: Operating System :: Microsoft :: Windows
Classifier: Operating System :: POSIX
Classifier: Operating System :: Unix
Classifier: Programming Language :: C++
Classifier: Programming Language :: Python
Classifier: Topic :: Scientific/Engineering
Classifier: Topic :: Scientific/Engineering :: Information Analysis
Classifier: Topic :: Scientific/Engineering :: Medical Science Apps.
Classifier: Topic :: Software Development :: Libraries
Project-URL: Download, https://github.com/InsightSoftwareConsortium/ITKIOMeshSTL
Project-URL: Homepage, https://github.com/InsightSoftwareConsortium/ITKIOMeshSTL
Requires-Python: >=3.9
Requires-Dist: itk-io==5.4.*
